README.rst
setup.py
pgsqlx/__init__.py
pgsqlx/constant.py
pgsqlx/db.py
pgsqlx/dbx.py
pgsqlx/log_support.py
pgsqlx/sql_mapper.py
pgsqlx.egg-info/PKG-INFO
pgsqlx.egg-info/SOURCES.txt
pgsqlx.egg-info/dependency_links.txt
pgsqlx.egg-info/not-zip-safe
pgsqlx.egg-info/requires.txt
pgsqlx.egg-info/top_level.txt