Metadata-Version: 2.1
Name: pgsqlx
Version: 2.1.4
Summary: A thread safe sql executor for PostgreSQL like MyBatis with connection pool. It helps you automatically manage database connections and transactions. It also provides ORM operations for single tables.
Home-page: https://gitee.com/summry/pgsqlx
Author: summy
Author-email: xiazhongbiao@126.com
License: UNKNOWN
Keywords: sql,PostgreSQL,MyBatis,python
Platform: UNKNOWN
Requires-Python: >=3.5
